auto_slugify/ fields.py
auto_slugify/__init__.py
django_auto_slugify-0.1.1.dist-info/licenses/LICENSE
django_auto_slugify-0.1.1.dist-info/METADATA
django_auto_slugify-0.1.1.dist-info/WHEEL
django_auto_slugify-0.1.1.dist-info/top_level.txt
django_auto_slugify-0.1.1.dist-info/RECORD
