Metadata-Version: 2.4
Name: django-auto-slugify
Version: 0.1.1
Summary: Auto-generate unique slugs for Django models
Home-page: https://github.com/programmerhasan/django-auto-slugify
Author: ProgrammerHasan
Author-email: programmerhasan@email.com
Classifier: Framework :: Django
Classifier: Programming Language :: Python :: 3
Classifier: License :: OSI Approved :: MIT License
Classifier: Operating System :: OS Independent
Requires-Python: >=3.7
License-File: LICENSE
Requires-Dist: Django>=3.2
Dynamic: author
Dynamic: author-email
Dynamic: classifier
Dynamic: description-content-type
Dynamic: home-page
Dynamic: license-file
Dynamic: requires-dist
Dynamic: requires-python
Dynamic: summary
